mr_graph/__init__.py
mr_graph/graph.py
mr_graph/graphio.py
mr_graph/node.py
mr_graph/node_data_aggregator.py
mr_graph/node_data_class.py
mr_graph/node_data_tracker.py
mr_graph-0.2.6.dist-info/LICENSE
mr_graph-0.2.6.dist-info/METADATA
mr_graph-0.2.6.dist-info/WHEEL
mr_graph-0.2.6.dist-info/top_level.txt
mr_graph-0.2.6.dist-info/zip-safe
mr_graph-0.2.6.dist-info/RECORD
