Metadata-Version: 2.1
Name: mr-graph
Version: 0.2.6
Summary: A graph definition execution library for async/sync python functions.
Home-page: https://mr-graph.readthedocs.io/en/latest/
Author: Jeremy McMinis
Author-email: jeremy@sawtoothdata.com
License: MIT
Keywords: graph,mr_graph
Classifier: License :: OSI Approved :: BSD License
Classifier: Programming Language :: Python :: 3
Requires-Python: >=3.7
License-File: LICENSE
Requires-Dist: pydantic (>1.0.0)
